ifclient/__init__.py
ifclient/api/__init__.py
ifclient/api/client.py
ifclient/cli.py
ifclient/commands/__init__.py
ifclient/commands/apply.py
ifclient/commands/generate.py
ifclient/commands/plan.py
ifclient/commands/validate.py
ifclient/config/__init__.py
ifclient/config/merger/__init__.py
ifclient/config/merger/v1/config_merge.py
ifclient/config/models/__init__.py
ifclient/config/models/common/__init__.py
ifclient/config/models/common/file_reference.py
ifclient/config/models/v1/__init__.py
ifclient/config/models/v1/component_metric.py
ifclient/config/models/v1/instance_grouping.py
ifclient/config/models/v1/project_base.py
ifclient/config/models/v1/tool_config.py
ifclient/config/validation/__init__.py
ifclient/config/validation/dispatcher.py
ifclient/exceptions/__init__.py
ifclient/exceptions/config.py
ifclient/utils/file_util.py
ifclient/utils/logger.py
insightfinder_client-0.1.0.dist-info/METADATA
insightfinder_client-0.1.0.dist-info/WHEEL
insightfinder_client-0.1.0.dist-info/entry_points.txt
insightfinder_client-0.1.0.dist-info/RECORD
