Metadata-Version: 2.4
Name: insightfinder-client
Version: 0.1.0
Summary: A CLI tool to configure and change InsightFinder project settings
Author: InsightFinder AI
Author-email: support@insightfinder.com
Requires-Python: >=3.12
Classifier: Programming Language :: Python :: 3
Classifier: Programming Language :: Python :: 3.12
Classifier: Programming Language :: Python :: 3.13
Classifier: Programming Language :: Python :: 3.14
Requires-Dist: click
Requires-Dist: pydantic
Requires-Dist: python-dotenv (>=1.0.1,<2.0.0)
Requires-Dist: pyyaml
Requires-Dist: requests (>=2.32.4)
Requires-Dist: urllib3 (>=2.5.0)
